replicate/__init__.py
replicate/_base_client.py
replicate/_client.py
replicate/_compat.py
replicate/_constants.py
replicate/_exceptions.py
replicate/_files.py
replicate/_models.py
replicate/_module_client.py
replicate/_qs.py
replicate/_resource.py
replicate/_response.py
replicate/_streaming.py
replicate/_types.py
replicate/_version.py
replicate/pagination.py
replicate/py.typed
replicate/_utils/__init__.py
replicate/_utils/_logs.py
replicate/_utils/_proxy.py
replicate/_utils/_reflection.py
replicate/_utils/_resources_proxy.py
replicate/_utils/_streams.py
replicate/_utils/_sync.py
replicate/_utils/_transform.py
replicate/_utils/_typing.py
replicate/_utils/_utils.py
replicate/lib/.keep
replicate/lib/_files.py
replicate/lib/_models.py
replicate/lib/_predictions.py
replicate/lib/_schema.py
replicate/resources/__init__.py
replicate/resources/account.py
replicate/resources/collections.py
replicate/resources/files.py
replicate/resources/hardware.py
replicate/resources/predictions.py
replicate/resources/trainings.py
replicate/resources/deployments/__init__.py
replicate/resources/deployments/deployments.py
replicate/resources/deployments/predictions.py
replicate/resources/models/__init__.py
replicate/resources/models/examples.py
replicate/resources/models/models.py
replicate/resources/models/predictions.py
replicate/resources/models/readme.py
replicate/resources/models/versions.py
replicate/resources/webhooks/__init__.py
replicate/resources/webhooks/webhooks.py
replicate/resources/webhooks/default/__init__.py
replicate/resources/webhooks/default/default.py
replicate/resources/webhooks/default/secret.py
replicate/types/__init__.py
replicate/types/account_get_response.py
replicate/types/deployment_create_params.py
replicate/types/deployment_create_response.py
replicate/types/deployment_get_response.py
replicate/types/deployment_list_response.py
replicate/types/deployment_update_params.py
replicate/types/deployment_update_response.py
replicate/types/file_create_params.py
replicate_stainless-0.6.0.dist-info/METADATA
replicate_stainless-0.6.0.dist-info/WHEEL
replicate_stainless-0.6.0.dist-info/licenses/LICENSE
replicate_stainless-0.6.0.dist-info/RECORD
